wfpc2tools/__init__.py
wfpc2tools/cwdutil.py
wfpc2tools/opusutil.py
wfpc2tools/wfpc2cte.py
wfpc2tools/wfpc2destreak.py
wfpc2tools/wfpc2util.py
wfpc2tools/tests/__init__.py
wfpc2tools/tests/test_noop.py
wfpc2tools-1.0.5.dist-info/LICENSE.txt
wfpc2tools-1.0.5.dist-info/METADATA
wfpc2tools-1.0.5.dist-info/WHEEL
wfpc2tools-1.0.5.dist-info/top_level.txt
wfpc2tools-1.0.5.dist-info/RECORD
